odoo8_addon_partner_sector-8.0.1.0.0.99.dev14-py2.7-nspkg.pth
odoo8_addon_partner_sector-8.0.1.0.0.99.dev14.dist-info/DESCRIPTION.rst
odoo8_addon_partner_sector-8.0.1.0.0.99.dev14.dist-info/METADATA
odoo8_addon_partner_sector-8.0.1.0.0.99.dev14.dist-info/RECORD
odoo8_addon_partner_sector-8.0.1.0.0.99.dev14.dist-info/WHEEL
odoo8_addon_partner_sector-8.0.1.0.0.99.dev14.dist-info/metadata.json
odoo8_addon_partner_sector-8.0.1.0.0.99.dev14.dist-info/namespace_packages.txt
odoo8_addon_partner_sector-8.0.1.0.0.99.dev14.dist-info/top_level.txt
odoo_addons/partner_sector/README.rst
odoo_addons/partner_sector/__init__.py
odoo_addons/partner_sector/__openerp__.py
odoo_addons/partner_sector/i18n/.gitkeep
odoo_addons/partner_sector/i18n/de.po
odoo_addons/partner_sector/i18n/es.po
odoo_addons/partner_sector/i18n/eu.po
odoo_addons/partner_sector/i18n/fi.po
odoo_addons/partner_sector/i18n/fr.po
odoo_addons/partner_sector/i18n/it.po
odoo_addons/partner_sector/i18n/partner_sector.pot
odoo_addons/partner_sector/i18n/sl.po
odoo_addons/partner_sector/models/__init__.py
odoo_addons/partner_sector/models/res_partner.py
odoo_addons/partner_sector/models/res_partner_sector.py
odoo_addons/partner_sector/security/ir.model.access.csv
odoo_addons/partner_sector/static/description/icon.png
odoo_addons/partner_sector/tests/__init__.py
odoo_addons/partner_sector/tests/test_res_partner.py
odoo_addons/partner_sector/views/res_partner_sector_view.xml
odoo_addons/partner_sector/views/res_partner_view.xml
